nc_to_gpkg/__init__.py
nc_to_gpkg/netcdf.py
nc_to_gpkg-0.0.8.dist-info/METADATA
nc_to_gpkg-0.0.8.dist-info/WHEEL
nc_to_gpkg-0.0.8.dist-info/top_level.txt
nc_to_gpkg-0.0.8.dist-info/RECORD
